bitex/__init__.py
bitex/bitex.py
bitex/block.py
bitex/exceptions.py
bitex/transactions.py
bitex_blockchain_explorer-0.1.1.dist-info/LICENSE
bitex_blockchain_explorer-0.1.1.dist-info/METADATA
bitex_blockchain_explorer-0.1.1.dist-info/WHEEL
bitex_blockchain_explorer-0.1.1.dist-info/top_level.txt
bitex_blockchain_explorer-0.1.1.dist-info/RECORD
