Metadata-Version: 2.1
Name: bitex-blockchain-explorer
Version: 0.1.1
Summary: A Python module for interacting with blockchain data using the Bitex blockchain explorer
Home-page: https://github.com/Kuduxaaa/bitex-blockchain-explorer
Author: Nika Kudukhashvili
Author-email: nikakuduxashvili0@gmail.com
Classifier: Programming Language :: Python :: 3
Classifier: License :: OSI Approved :: MIT License
Classifier: Operating System :: OS Independent
Requires-Python: >=3.6
License-File: LICENSE
Provides-Extra: dev
Requires-Dist: pytest ; extra == 'dev'
Requires-Dist: mypy ; extra == 'dev'
